bettercli/__init__.py
bettercli/cli.py
bettercli/command.py
bettercli/decorators.py
bettercli/exceptions.py
bettercli/logger.py
bettercli/option.py
bettercli/utils.py
bettercli-0.1.0.dist-info/LICENSE
bettercli-0.1.0.dist-info/METADATA
bettercli-0.1.0.dist-info/WHEEL
bettercli-0.1.0.dist-info/top_level.txt
bettercli-0.1.0.dist-info/RECORD
